fastapi_quickstart/__init__.py
fastapi_quickstart/__main__.py
fastapi_quickstart/main.py
fastapi_quickstart/templates/main.py.template
fastapi_quickstart/templates/models.py.template
fastapi_quickstart/templates/requirements.txt.template
fastapi_quickstart_genesis-0.1.3.dist-info/LICENSE
fastapi_quickstart_genesis-0.1.3.dist-info/METADATA
fastapi_quickstart_genesis-0.1.3.dist-info/WHEEL
fastapi_quickstart_genesis-0.1.3.dist-info/entry_points.txt
fastapi_quickstart_genesis-0.1.3.dist-info/top_level.txt
fastapi_quickstart_genesis-0.1.3.dist-info/RECORD
