Metadata-Version: 2.1
Name: fastapi-quickstart-genesis
Version: 0.1.3
Summary: A quick start tool for FastAPI projects
Home-page: https://github.com/ackmanb/fastapi-quickstart
Author: JCN
Author-email: ackmanb@gmail.com
Classifier: Programming Language :: Python :: 3
Classifier: License :: OSI Approved :: MIT License
Classifier: Operating System :: OS Independent
Requires-Python: >=3.7
License-File: LICENSE
Requires-Dist: fastapi>=0.68.0
Requires-Dist: uvicorn>=0.15.0
